setup.py
txjason/__init__.py
txjason/client.py
txjason/handler.py
txjason/netstring.py
txjason/protocol.py
txjason/service.py
txjason.egg-info/PKG-INFO
txjason.egg-info/SOURCES.txt
txjason.egg-info/dependency_links.txt
txjason.egg-info/top_level.txt