Metadata-Version: 1.0
Name: txjason
Version: 0.1.0
Summary: Twisted jsonrpc 2.0 module
Home-page: https://github.com/flowroute/txjason
Author: Flowroute LLC
Author-email: matthew@flowroute.com
License: UNKNOWN
Platform: UNKNOWN
